Metadata-Version: 2.1
Name: gluon2keras
Version: 0.0.1
Summary: The deep learning models convertor
Home-page: https://github.com/nerox8664/gluon2keras
Author: Grigory Malivenko
Author-email: nerox8664@gmail.com
License: MIT
Platform: UNKNOWN
